astroedu/__build__.py
astroedu/__init__.py
astroedu/__main__.py
astroedu/classes/Body.py
astroedu/classes/__init__.py
astroedu/constants/__init__.py
astroedu/constants/constants.py
astroedu/datasets/README.md
astroedu/datasets/__init__.py
astroedu/datasets/atmospheres.csv
astroedu/datasets/atmospheres.txt
astroedu/datasets/earth_chem_crust.csv
astroedu/datasets/earth_chem_crust.txt
astroedu/datasets/earth_chem_interior.csv
astroedu/datasets/earth_chem_interior.txt
astroedu/datasets/exobase.csv
astroedu/datasets/exobase.txt
astroedu/datasets/geotherm.csv
astroedu/datasets/geotherm.txt
astroedu/datasets/geotherm_original.csv
astroedu/datasets/geotherm_original.txt
astroedu/datasets/int_std_atm.csv
astroedu/datasets/int_std_atm.txt
astroedu/datasets/jupiter_moons.csv
astroedu/datasets/jupiter_moons.txt
astroedu/datasets/mass16.csv
astroedu/datasets/mass16.txt
astroedu/datasets/mass16Abundant.csv
astroedu/datasets/mass16Abundant.txt
astroedu/datasets/neptune_moons.csv
astroedu/datasets/neptune_moons.txt
astroedu/datasets/planetary_rings.csv
astroedu/datasets/planetary_rings.txt
astroedu/datasets/planets.csv
astroedu/datasets/planets.txt
astroedu/datasets/saturn_moons.csv
astroedu/datasets/saturn_moons.txt
astroedu/datasets/saturn_rings.csv
astroedu/datasets/saturn_rings.txt
astroedu/datasets/structure.csv
astroedu/datasets/structure.txt
astroedu/datasets/uranus_moons.csv
astroedu/datasets/uranus_moons.txt
astroedu/functions/__init__.py
astroedu/functions/functions.py
astroedu/interactives/blackbody_curves.ipynb
astroedu/interactives/equilibrium_temperature.ipynb
astroedu/interactives/stefan_boltzman_law.ipynb
astroedu/interactives/wiens_law.ipynb
astroedu/planetmagfields/LICENSE
astroedu/planetmagfields/README.md
astroedu/planetmagfields/__init__.py
astroedu/planetmagfields/libbfield.py
astroedu/planetmagfields/libgauss.py
astroedu/planetmagfields/planet.py
astroedu/planetmagfields/plotlib.py
astroedu/planetmagfields/potextra.py
astroedu/planetmagfields/utils.py
astroedu-0.4.3a0.dist-info/LICENSE
astroedu-0.4.3a0.dist-info/METADATA
astroedu-0.4.3a0.dist-info/WHEEL
astroedu-0.4.3a0.dist-info/entry_points.txt
astroedu-0.4.3a0.dist-info/top_level.txt
astroedu-0.4.3a0.dist-info/RECORD
