Metadata-Version: 2.1
Name: astroedu
Version: 0.4.3a0
Summary: A python package for astronomy educators
Home-page: https://github.com/astroDimitrios/astroedu
Author: Dimitrios Theodorakis
Author-email: astrodimitrios@gmail.com
License: UNKNOWN
Project-URL: Bug Tracker, https://github.com/astroDimitrios/astroedu/issues
Keywords: astronomy education astrophysics
Platform: UNKNOWN
Classifier: Development Status :: 3 - Alpha
Classifier: Programming Language :: Python :: 3
Classifier: License :: OSI Approved :: GNU General Public License v3 (GPLv3)
Classifier: Operating System :: OS Independent
Requires-Python: >=3.7
License-File: LICENSE
Requires-Dist: numpy (>=1.20.0)
Requires-Dist: scipy (>=1.6.0)
Requires-Dist: matplotlib (>=3.3.0)
Requires-Dist: pandas (>=1.1)
Requires-Dist: jupyterlab (>=3.0.0)
Requires-Dist: ipywidgets (>=7.6.0)
Requires-Dist: fire (>=0.4.0)
Requires-Dist: importlib-resources (>=5.1.2)
